{
    "2b195840412440a3b0de056720d97135": {
        "displayName": "KainSkywind",
        "externalPlatforms": [
            {
                "type": "nintendo",
                "displayName": "KainSkywind"
            },
            {
                "type": "psn",
                "displayName": "KainSkywind"
            }
        ]
    },
    "280723989df24cd687a3b35ebfcc670d": {
        "displayName": "KINGDREda1st",
        "externalPlatforms": [
            {
                "type": "psn",
                "displayName": "KINGDREda1st"
            }
        ]
    },
    "e6038f0563724dd5b6fec67def3c3a86": {
        "displayName": "ouibstir",
        "externalPlatforms": [
            {
                "type": "xbl",
                "displayName": "ouibstir"
            },
            {
                "type": "nintendo",
                "displayName": "ouibstir"
            }
        ]
    },
    "17ac9bfdb8ed4277bb719aa3ee6d1659": {
        "displayName": "Snyper1Zombie",
        "externalPlatforms": [
            {
                "type": "xbl",
                "displayName": "Snyper1Zombie"
            }
        ]
    },
    "ee57bdb98e7a428d88d5e9aeff6f5eb5": {
        "displayName": "MortalSkills",
        "externalPlatforms": [
            {
                "type": "xbl",
                "displayName": "Mortal Skills"
            },
            {
                "type": "steam",
                "displayName": "Mortal"
            },
            {
                "type": "psn",
                "displayName": "MortalTheGreat"
            }
        ]
    },
    "16346f8ff5554fe6be753cf9e5a644f2": {
        "displayName": "Skooks146",
        "externalPlatforms": [
            {
                "type": "xbl",
                "displayName": "Skooks6822"
            },
            {
                "type": "nintendo",
                "displayName": "Skooks146"
            },
            {
                "type": "psn",
                "displayName": "Skooks_146"
            }
        ]
    },
    "66a7d6b62f0d4b1aa899bc2e62261456": {
        "displayName": "ILoveLolaBunny",
        "externalPlatforms": [
            {
                "type": "xbl",
                "displayName": "AmFrijol"
            }
        ]
    },
    "f99e2081fa2b4f15974965ded008962e": {
        "displayName": "navid_dewman",
        "externalPlatforms": [
            {
                "type": "psn",
                "displayName": "newmandnyem"
            }
        ]
    },
    "bede480d7b394d998ac62ab9d05f6267": {
        "displayName": "Waba_25",
        "externalPlatforms": [
            {
                "type": "xbl",
                "displayName": "xxWABAxx"
            }
        ]
    },
    "7a50d842ea31461fb0e3288bb185dd18": {
        "displayName": "cobalt.exe",
        "externalPlatforms": [
            {
                "type": "xbl",
                "displayName": "VossXLV"
            },
            {
                "type": "steam",
                "displayName": "Cobalt"
            }
        ]
    },
    "26efebbef66043528433084a7af6f3d4": {
        "displayName": "G\u1d63\u2091\u2091n",
        "externalPlatforms": [
            {
                "type": "xbl",
                "displayName": "Greeennnnn7380"
            },
            {
                "type": "nintendo",
                "displayName": "G\u1d63\u2091\u2091n"
            },
            {
                "type": "psn",
                "displayName": "xiKraah"
            }
        ]
    },
    "0038bdd9b9fb4080bc934b0ec0a397e4": {
        "displayName": "Glizzyfordayz",
        "externalPlatforms": [
            {
                "type": "xbl",
                "displayName": "Hawkbad"
            },
            {
                "type": "nintendo",
                "displayName": "Glizzyfordayz"
            },
            {
                "type": "psn",
                "displayName": "Aidsfordayss"
            }
        ]
    },
    "44e2d5781b0142f7a54fc6d1fcbcada4": {
        "displayName": "tjtillman",
        "externalPlatforms": [
            {
                "type": "xbl",
                "displayName": "tjtillman06"
            },
            {
                "type": "nintendo",
                "displayName": "tjtillman"
            }
        ]
    },
    "734f9e42e3f343b283740f07420fc843": {
        "displayName": "QuadMold121",
        "externalPlatforms": [
            {
                "type": "xbl",
                "displayName": "QuadMold121"
            }
        ]
    },
    "b15de021bcc14c90a4d6a64c6138ad05": {
        "displayName": "AsapOso",
        "externalPlatforms": [
            {
                "type": "xbl",
                "displayName": "ASAP Oso"
            },
            {
                "type": "nintendo",
                "displayName": "AsapOso"
            }
        ]
    },
    "e6bef49f3dcc4beb9917accbfb5d1514": {
        "displayName": "Savage LaFlame",
        "externalPlatforms": []
    },
    "5803d8c89a814160ad36a6e8f4b0e59d": {
        "displayName": "Shawsberry93",
        "externalPlatforms": [
            {
                "type": "xbl",
                "displayName": "Shawsberry"
            },
            {
                "type": "steam",
                "displayName": "Shawsberry 93"
            },
            {
                "type": "psn",
                "displayName": "Shawsberry93"
            }
        ]
    },
    "c417dd76164b40dfb20fe7ff83e369fc": {
        "displayName": "jizlewright",
        "externalPlatforms": [
            {
                "type": "xbl",
                "displayName": "GeoLeo"
            },
            {
                "type": "steam",
                "displayName": "jizlewright"
            }
        ]
    },
    "0e36f3ba772e4085bf704c2faaa03cf7": {
        "displayName": "Barnacleez1",
        "externalPlatforms": [
            {
                "type": "xbl",
                "displayName": "Barnacleez"
            }
        ]
    },
    "80a441092d7346b29c6e3ce44b86781a": {
        "displayName": "MattMagnetic",
        "externalPlatforms": [
            {
                "type": "xbl",
                "displayName": "XxxACID KINGxxX"
            },
            {
                "type": "nintendo",
                "displayName": "MattMagnetic"
            },
            {
                "type": "psn",
                "displayName": "CorpseMechanical"
            }
        ]
    },
    "6c4d80b113494f9892058448f423b6eb": {
        "displayName": "X_charitard_X",
        "externalPlatforms": [
            {
                "type": "xbl",
                "displayName": "Gamertagx22"
            },
            {
                "type": "nintendo",
                "displayName": "X_charitard_X"
            },
            {
                "type": "psn",
                "displayName": "BennyBoy11506"
            }
        ]
    },
    "09d060a9855242c2b4432f0020a7195e": {
        "displayName": "EEPKane",
        "externalPlatforms": [
            {
                "type": "xbl",
                "displayName": "EEP Kane"
            },
            {
                "type": "nintendo",
                "displayName": "EEPKane"
            },
            {
                "type": "psn",
                "displayName": "EEPKane"
            }
        ]
    },
    "2d8ce0811476489bbecafa1f2f87ec7b": {
        "displayName": "smelley",
        "externalPlatforms": [
            {
                "type": "steam",
                "displayName": "snack master (real)"
            },
            {
                "type": "psn",
                "displayName": "smelley_"
            }
        ]
    },
    "19ae2053378e42f3af41aed8338644fd": {
        "displayName": "boohbahstank",
        "externalPlatforms": [
            {
                "type": "xbl",
                "displayName": "Boohbahstank"
            }
        ]
    },
    "a039d30077a74a9893876fbc4173bdc0": {
        "displayName": "RDZmichael",
        "externalPlatforms": [
            {
                "type": "xbl",
                "displayName": "RDZmichael"
            },
            {
                "type": "nintendo",
                "displayName": "RDZmichael"
            },
            {
                "type": "steam",
                "displayName": "RDZmichael"
            },
            {
                "type": "psn",
                "displayName": "RDZmichael"
            }
        ]
    },
    "84f86bcf63014baebf059f755418e678": {
        "displayName": "Charlster",
        "externalPlatforms": [
            {
                "type": "xbl",
                "displayName": "Charlster10"
            },
            {
                "type": "nintendo",
                "displayName": "Charlster"
            },
            {
                "type": "steam",
                "displayName": "Charlster"
            },
            {
                "type": "psn",
                "displayName": "CharlsterPS"
            }
        ]
    },
    "db6771a1163b49119e97dafc2c43e198": {
        "displayName": "Etherea2Coul",
        "externalPlatforms": [
            {
                "type": "xbl",
                "displayName": "Ethereal2Coul"
            },
            {
                "type": "steam",
                "displayName": "LowlyTechnologist"
            },
            {
                "type": "psn",
                "displayName": "Ethereal2Coul"
            }
        ]
    },
    "25995b5820a04ac281229b1b44211eca": {
        "displayName": "pierutus",
        "externalPlatforms": [
            {
                "type": "nintendo",
                "displayName": "pierutus"
            },
            {
                "type": "steam",
                "displayName": "frt"
            },
            {
                "type": "psn",
                "displayName": "gozzu_"
            }
        ]
    },
    "5098e0476b5045be8b2c1bfa3241a185": {
        "displayName": "Hmmm404",
        "externalPlatforms": [
            {
                "type": "xbl",
                "displayName": "z404z5511"
            }
        ]
    },
    "309d6a67ca7f465b9797a32579c10ca3": {
        "displayName": "kevkev993",
        "externalPlatforms": [
            {
                "type": "psn",
                "displayName": "Hedoniistic"
            }
        ]
    },
    "fbee175848f048e79840787884658938": {
        "displayName": "Mc_thicky",
        "externalPlatforms": [
            {
                "type": "psn",
                "displayName": "TWISTED_BULLETT"
            }
        ]
    },
    "b81106a075ab48e3aa00f2941de83cf5": {
        "displayName": "CULER1N",
        "externalPlatforms": [
            {
                "type": "xbl",
                "displayName": "xNvDyCulerin Bz"
            },
            {
                "type": "psn",
                "displayName": "xNvDyCulerin"
            }
        ]
    },
    "f28a7101837e405e9f7b14d02a2965d7": {
        "displayName": "Ing-Dono",
        "externalPlatforms": [
            {
                "type": "xbl",
                "displayName": "Ingmar75"
            },
            {
                "type": "nintendo",
                "displayName": "Ing-Dono"
            },
            {
                "type": "steam",
                "displayName": "Ing-Dono"
            }
        ]
    },
    "d8932a5826d24d30958207cb2bf4b7a4": {
        "displayName": "BubblegumGrunge",
        "externalPlatforms": [
            {
                "type": "xbl",
                "displayName": "PastelRoseFairy"
            },
            {
                "type": "nintendo",
                "displayName": "BubblegumGrunge"
            },
            {
                "type": "steam",
                "displayName": "\u00bbBubblegum Grunge"
            },
            {
                "type": "psn",
                "displayName": "JohtoTheAverage"
            }
        ]
    },
    "457aab6ee79445fcb80900946b77eb91": {
        "displayName": "kidcode46",
        "externalPlatforms": [
            {
                "type": "xbl",
                "displayName": "kidcode10"
            },
            {
                "type": "nintendo",
                "displayName": "kidcode46"
            }
        ]
    },
    "d26fb00982c842a6bdc518c664a2691f": {
        "displayName": "McSaac",
        "externalPlatforms": [
            {
                "type": "xbl",
                "displayName": "IzzyMcSaac"
            },
            {
                "type": "psn",
                "displayName": "Pvtcaboose13"
            }
        ]
    },
    "011fdd4c93144654987f829c217ebac1": {
        "displayName": "Alice the Menace",
        "externalPlatforms": [
            {
                "type": "nintendo",
                "displayName": "Alice the Menace"
            },
            {
                "type": "steam",
                "displayName": "Alice_the_Menace"
            },
            {
                "type": "psn",
                "displayName": "Al1ce_the_Menace"
            }
        ]
    },
    "d8d01c270d85477fbb28b68f451f2e4f": {
        "displayName": "NarDarkk",
        "externalPlatforms": [
            {
                "type": "steam",
                "displayName": "NarDarkk"
            }
        ]
    },
    "0c89ef2ff7be4cd982cb9958898356e0": {
        "displayName": "GhostlyObserver",
        "externalPlatforms": [
            {
                "type": "nintendo",
                "displayName": "GhostlyObserver"
            },
            {
                "type": "steam",
                "displayName": "Daft Crunk"
            },
            {
                "type": "psn",
                "displayName": "GhostlyGamer863"
            }
        ]
    },
    "1c9cdacc423f48f0984d4b9d1ce87281": {
        "displayName": "msmct2011",
        "externalPlatforms": [
            {
                "type": "xbl",
                "displayName": "SaffronRobin468"
            },
            {
                "type": "psn",
                "displayName": "msmct2011"
            }
        ]
    },
    "7e0fd45eba804dd4b3425d7c21606b50": {
        "displayName": "FlandersRex",
        "externalPlatforms": [
            {
                "type": "xbl",
                "displayName": "FlandersRex"
            },
            {
                "type": "nintendo",
                "displayName": "FlandersRex"
            },
            {
                "type": "steam",
                "displayName": "FlandersRex"
            }
        ]
    },
    "1142bb677472435b993f43ffaef5dc70": {
        "displayName": "ReflinBow",
        "externalPlatforms": [
            {
                "type": "xbl",
                "displayName": "RegentBow937830"
            }
        ]
    },
    "81274b5f18464072b9aa09ef9d7b62a9": {
        "displayName": "Tigre5012",
        "externalPlatforms": [
            {
                "type": "xbl",
                "displayName": "TigreDemeo5012"
            },
            {
                "type": "nintendo",
                "displayName": "Tigre5012"
            },
            {
                "type": "steam",
                "displayName": "Tigre"
            },
            {
                "type": "psn",
                "displayName": "LeftBehind2211"
            }
        ]
    },
    "f83136e62806428f885fb5a113c54ba6": {
        "displayName": "MyNameJavi",
        "externalPlatforms": [
            {
                "type": "steam",
                "displayName": "MyNameJavi"
            }
        ]
    },
    "d907fed357294a488771af2a9f6da046": {
        "displayName": "peppapigfan38",
        "externalPlatforms": [
            {
                "type": "steam",
                "displayName": "hayden bo bayden"
            }
        ]
    },
    "de385e9f8e3e4bc98631098e50588ece": {
        "displayName": "A2lander",
        "externalPlatforms": [
            {
                "type": "xbl",
                "displayName": "X 2lander"
            },
            {
                "type": "steam",
                "displayName": "A2lander"
            },
            {
                "type": "psn",
                "displayName": "ATjulander"
            }
        ]
    },
    "acb1287ae2b34024aac1a972209f0745": {
        "displayName": "hitchplum",
        "externalPlatforms": [
            {
                "type": "xbl",
                "displayName": "HitchedPlum37"
            }
        ]
    },
    "364f2148f7964cbbbf6c399ccc91a700": {
        "displayName": "an Emotional Bi",
        "externalPlatforms": [
            {
                "type": "xbl",
                "displayName": "an Emotional Bi"
            },
            {
                "type": "nintendo",
                "displayName": "an Emotional Bi"
            },
            {
                "type": "steam",
                "displayName": "I Paid for WinRAR"
            }
        ]
    },
    "0ace62864b0743cfa523db6613b5a8b7": {
        "displayName": "PistolPete2k3_",
        "externalPlatforms": [
            {
                "type": "xbl",
                "displayName": "PistolPete2k3"
            },
            {
                "type": "nintendo",
                "displayName": "PistolPete2k3_"
            },
            {
                "type": "steam",
                "displayName": "PistolPete2k3"
            },
            {
                "type": "psn",
                "displayName": "PistolPete2k3"
            }
        ]
    },
    "1fb6529839da4796aad05d30579c3948": {
        "displayName": "GENHARTALLCAPS",
        "externalPlatforms": [
            {
                "type": "xbl",
                "displayName": "ididnaahht"
            },
            {
                "type": "psn",
                "displayName": "solvemymaze"
            }
        ]
    },
    "2c0a36a6875b4c97b587b3f3e6911125": {
        "displayName": "Touch_Of_Gray",
        "externalPlatforms": [
            {
                "type": "xbl",
                "displayName": "Touch0fGray"
            },
            {
                "type": "nintendo",
                "displayName": "Touch_Of_Gray"
            },
            {
                "type": "steam",
                "displayName": "Touch of Gray"
            }
        ]
    },
    "8a4c314b4f004195b15cfa694b1b92f0": {
        "displayName": "Rhinobug64",
        "externalPlatforms": [
            {
                "type": "xbl",
                "displayName": "Rhinobug64"
            },
            {
                "type": "steam",
                "displayName": "Rhino64"
            },
            {
                "type": "psn",
                "displayName": "Rhinostar64"
            }
        ]
    },
    "2e348bf776f14cf48d4798bfc801b56d": {
        "displayName": "iM_A_F90_ScRuB_",
        "externalPlatforms": [
            {
                "type": "xbl",
                "displayName": "iM A F90 ScRuB"
            },
            {
                "type": "steam",
                "displayName": "SPECTER"
            },
            {
                "type": "psn",
                "displayName": "iM_A_F90_ScRuB_"
            }
        ]
    },
    "fb6989e9a4ba42698b6a732853aaad85": {
        "displayName": "HearYouMe2002",
        "externalPlatforms": [
            {
                "type": "steam",
                "displayName": "Hear"
            },
            {
                "type": "psn",
                "displayName": "Juanchi__2002__"
            }
        ]
    },
    "8ad0c6ad01e0450d8e7cefffa6ac6a9e": {
        "displayName": "ToneMeisterFlex",
        "externalPlatforms": [
            {
                "type": "psn",
                "displayName": "TonMiesterFlex"
            }
        ]
    },
    "b876b03c23184aa69a44ad9aa937ed82": {
        "displayName": "RazmanianDevil95",
        "externalPlatforms": [
            {
                "type": "xbl",
                "displayName": "xRyanOConnor95x"
            },
            {
                "type": "psn",
                "displayName": "xRyanOConnor-95x"
            }
        ]
    },
    "59493bf296f649039ecb080960ffbba5": {
        "displayName": "Mr.Mulletproof",
        "externalPlatforms": [
            {
                "type": "nintendo",
                "displayName": "Mr.Mulletproof"
            },
            {
                "type": "steam",
                "displayName": "Poggies"
            },
            {
                "type": "psn",
                "displayName": "MrMulletproof"
            }
        ]
    },
    "c0562fab42404a60b34930e97729a1b1": {
        "displayName": "Dime AU",
        "externalPlatforms": [
            {
                "type": "xbl",
                "displayName": "Dime AU"
            },
            {
                "type": "steam",
                "displayName": "Dime"
            },
            {
                "type": "psn",
                "displayName": "x_IDIMEBAG_x"
            }
        ]
    },
    "57be4d07e57d47f3a6900a7c7ed18390": {
        "displayName": "ClassicSZN",
        "externalPlatforms": [
            {
                "type": "steam",
                "displayName": "classic"
            }
        ]
    },
    "6d943b1668d34dc2b6471854a8f7758a": {
        "displayName": "have.a.day",
        "externalPlatforms": [
            {
                "type": "nintendo",
                "displayName": "have.a.day"
            }
        ]
    },
    "20910bd48ad24714bf878e523b60eba3": {
        "displayName": "Reef_side",
        "externalPlatforms": [
            {
                "type": "xbl",
                "displayName": "Reef2928"
            },
            {
                "type": "psn",
                "displayName": "Reef2928"
            }
        ]
    },
    "298dafc9f8dc4edaa628220d057c9f21": {
        "displayName": "Cozzy_148",
        "externalPlatforms": [
            {
                "type": "xbl",
                "displayName": "Cozzy 148"
            },
            {
                "type": "psn",
                "displayName": "Cozzy_148"
            }
        ]
    },
    "572bd5a7b4874ca3a3cdf2f7440d7e0d": {
        "displayName": "Tornadica",
        "externalPlatforms": [
            {
                "type": "steam",
                "displayName": "Tornadica"
            }
        ]
    },
    "14ccb3d6f56b4921b54661b40ac0b0cf": {
        "displayName": "Nyxilll",
        "externalPlatforms": [
            {
                "type": "xbl",
                "displayName": "Nyxil"
            }
        ]
    },
    "710b6b21408d4e969e55ca1f7a6dd3dc": {
        "displayName": "IGR Erebus",
        "externalPlatforms": [
            {
                "type": "xbl",
                "displayName": "IGR Erebus"
            },
            {
                "type": "nintendo",
                "displayName": "IGR Erebus"
            },
            {
                "type": "steam",
                "displayName": "IGR Erebus"
            },
            {
                "type": "psn",
                "displayName": "IGRErebus"
            }
        ]
    },
    "f087914527514cb3a48b6ce7ad51c419": {
        "displayName": "ianskk",
        "externalPlatforms": [
            {
                "type": "nintendo",
                "displayName": "ianskk"
            },
            {
                "type": "steam",
                "displayName": "itsIan"
            }
        ]
    },
    "c44dee7e681b40689aab2c8e5fe31c4e": {
        "displayName": "Madtown B",
        "externalPlatforms": [
            {
                "type": "xbl",
                "displayName": "Madtown B"
            }
        ]
    },
    "a191a4bb8d8b49aaac85d67e6ef4b501": {
        "displayName": "Owlgoblin77",
        "externalPlatforms": [
            {
                "type": "xbl",
                "displayName": "OwlGoblin77"
            }
        ]
    },
    "0672e6f1ac874ccf90561301246a49c3": {
        "displayName": "SuohW",
        "externalPlatforms": [
            {
                "type": "xbl",
                "displayName": "SuohW"
            }
        ]
    },
    "ea48473f27fb49e2a463ac9b6480904d": {
        "displayName": "marshude",
        "externalPlatforms": [
            {
                "type": "xbl",
                "displayName": "marshude1"
            },
            {
                "type": "steam",
                "displayName": "marsdude"
            },
            {
                "type": "psn",
                "displayName": "marshude1"
            }
        ]
    },
    "88a01f8f0f134d96812f53209a758dd2": {
        "displayName": "CuteEevee lol",
        "externalPlatforms": [
            {
                "type": "xbl",
                "displayName": "FNAF MASTER5691"
            }
        ]
    },
    "aec67efdec04456aafa8444634bb4254": {
        "displayName": "b1urple",
        "externalPlatforms": [
            {
                "type": "nintendo",
                "displayName": "b1urple"
            }
        ]
    },
    "5921e3e0d4834eb5ab3cf578c62177cc": {
        "displayName": "Russwsx",
        "externalPlatforms": [
            {
                "type": "xbl",
                "displayName": "russwsx"
            }
        ]
    },
    "fe334415a5e74c72a0fafa96d7fe860e": {
        "displayName": "JJBOCC",
        "externalPlatforms": [
            {
                "type": "xbl",
                "displayName": "JJBOCC"
            }
        ]
    },
    "80c69758e2794410afca93b4b8954025": {
        "displayName": "xOGx RockStaRs",
        "externalPlatforms": [
            {
                "type": "xbl",
                "displayName": "xOGx RockStaRs"
            },
            {
                "type": "nintendo",
                "displayName": "xOGx RockStaRs"
            },
            {
                "type": "steam",
                "displayName": "xOGx RockStaRs"
            },
            {
                "type": "psn",
                "displayName": "xOGxRockStaRs"
            }
        ]
    },
    "e2e6b6978204416da9e03bc09a7713a0": {
        "displayName": "Skeletonking910",
        "externalPlatforms": [
            {
                "type": "xbl",
                "displayName": "Skeletonking910"
            },
            {
                "type": "steam",
                "displayName": "Skeletonking"
            },
            {
                "type": "psn",
                "displayName": "Skeletonking911"
            }
        ]
    },
    "5e1c52de774841cba97abf12a543e628": {
        "displayName": "IrishShadow07",
        "externalPlatforms": [
            {
                "type": "xbl",
                "displayName": "IrishShadow7"
            },
            {
                "type": "nintendo",
                "displayName": "IrishShadow07"
            }
        ]
    },
    "28f9eb3cdcc14b19b000dfc9b3f80cbc": {
        "displayName": "tibblesxdd",
        "externalPlatforms": [
            {
                "type": "xbl",
                "displayName": "Tommy Tibbles"
            },
            {
                "type": "nintendo",
                "displayName": "tibblesxdd"
            }
        ]
    },
    "d701b36896e74e87a473b1665c561500": {
        "displayName": "blink 1826969",
        "externalPlatforms": [
            {
                "type": "xbl",
                "displayName": "blink 1826969"
            }
        ]
    },
    "f38b8d3494504c31924d93f98818bef2": {
        "displayName": "Hoovehh",
        "externalPlatforms": [
            {
                "type": "nintendo",
                "displayName": "Hoovehh"
            },
            {
                "type": "steam",
                "displayName": "Hooveh"
            },
            {
                "type": "psn",
                "displayName": "Hooveh"
            }
        ]
    },
    "767a63844a6643a8bae5154494092f51": {
        "displayName": "DonBlucci",
        "externalPlatforms": [
            {
                "type": "psn",
                "displayName": "Blucci"
            }
        ]
    },
    "53fbd4adc7c3406b988861ca37bf487f": {
        "displayName": "BodeJazz",
        "externalPlatforms": [
            {
                "type": "xbl",
                "displayName": "BodeJazz"
            },
            {
                "type": "steam",
                "displayName": "KiyKatze Bodie"
            },
            {
                "type": "psn",
                "displayName": "BodeJazz"
            }
        ]
    },
    "c386ee9b53374081a10e4442305f4745": {
        "displayName": "GizmoRace",
        "externalPlatforms": []
    },
    "0df70ba09c884227935adc816e4b47c6": {
        "displayName": "GravityeeControl",
        "externalPlatforms": [
            {
                "type": "steam",
                "displayName": "SyncNero"
            }
        ]
    },
    "6420c232311d4ae8b3abebc277428994": {
        "displayName": "MudLeak",
        "externalPlatforms": [
            {
                "type": "xbl",
                "displayName": "MudLeak"
            },
            {
                "type": "nintendo",
                "displayName": "MudLeak"
            },
            {
                "type": "psn",
                "displayName": "MudLeak"
            }
        ]
    },
    "2982f0a92f6c4488a304c9cca3ecc959": {
        "displayName": "FriendsofFes",
        "externalPlatforms": [
            {
                "type": "xbl",
                "displayName": "FriendsofFes"
            }
        ]
    },
    "d9d77fa785a9492ea9e25cb9fda5c5a8": {
        "displayName": "Rendsay",
        "externalPlatforms": [
            {
                "type": "nintendo",
                "displayName": "Rendsay"
            },
            {
                "type": "steam",
                "displayName": "Weeb"
            },
            {
                "type": "psn",
                "displayName": "rendsay"
            }
        ]
    },
    "b9a41d40716541ebb9ca4292e72cfb87": {
        "displayName": "asdfg54355",
        "externalPlatforms": [
            {
                "type": "psn",
                "displayName": "asdfg54355"
            }
        ]
    },
    "4801a23105444404876b66bccd0daaa4": {
        "displayName": "Hyunga93",
        "externalPlatforms": []
    },
    "052103099bda4f9c8ddb416d672c20de": {
        "displayName": "Shadow_L8er",
        "externalPlatforms": [
            {
                "type": "nintendo",
                "displayName": "Shadow_L8er"
            },
            {
                "type": "psn",
                "displayName": "ShadowL8er9"
            }
        ]
    },
    "f38751b4dc7c457daba578bfa844de00": {
        "displayName": "Chungunlunges",
        "externalPlatforms": [
            {
                "type": "xbl",
                "displayName": "HotScarface4013"
            },
            {
                "type": "nintendo",
                "displayName": "Chungunlunges"
            },
            {
                "type": "steam",
                "displayName": "HotScarface"
            }
        ]
    },
    "1ab14168fda44560a5cf33db88f8e3a4": {
        "displayName": "MrMcHaggis666",
        "externalPlatforms": [
            {
                "type": "psn",
                "displayName": "Mr_Mc_Haggis"
            }
        ]
    },
    "d33ff4415a5445c38f876d9b997e6812": {
        "displayName": "gilvalgai",
        "externalPlatforms": [
            {
                "type": "xbl",
                "displayName": "gilvalgai"
            },
            {
                "type": "nintendo",
                "displayName": "gilvalgai"
            }
        ]
    },
    "a80e700cf1c948f78d6538b3c2c67616": {
        "displayName": "iPad joshi",
        "externalPlatforms": [
            {
                "type": "xbl",
                "displayName": "jaxisamonke"
            }
        ]
    },
    "2a4e0f665f9a47db8bc66775acbdbf06": {
        "displayName": "Undatedeagle",
        "externalPlatforms": [
            {
                "type": "xbl",
                "displayName": "UndatedEagle93"
            }
        ]
    },
    "793f180a0d5a48a8a44f4584cf5fc072": {
        "displayName": "McLovin241300",
        "externalPlatforms": [
            {
                "type": "xbl",
                "displayName": "KitCarloMagn596"
            },
            {
                "type": "nintendo",
                "displayName": "McLovin241300"
            }
        ]
    },
    "a3b96388dce34766b0eaeccd4c164e2b": {
        "displayName": "Tyrandadino",
        "externalPlatforms": [
            {
                "type": "xbl",
                "displayName": "Tyrandadino"
            }
        ]
    },
    "92c292cbf03c4c3aaabca0c58249841a": {
        "displayName": "Adairn101",
        "externalPlatforms": [
            {
                "type": "xbl",
                "displayName": "adairn101"
            },
            {
                "type": "nintendo",
                "displayName": "Adairn101"
            },
            {
                "type": "steam",
                "displayName": "adairn_"
            }
        ]
    },
    "0cfead32b1e84d3ebe8645b1fffd60f6": {
        "displayName": "BindedByBanshees",
        "externalPlatforms": [
            {
                "type": "psn",
                "displayName": "BindedByBanshees"
            }
        ]
    },
    "ddd8368b407d4f938fd680bcdb2d1a58": {
        "displayName": "CamBlack",
        "externalPlatforms": [
            {
                "type": "xbl",
                "displayName": "CamBlack2011"
            },
            {
                "type": "nintendo",
                "displayName": "CamBlack"
            }
        ]
    }
}