{
    "3a37ac3cf72146aa86810a643c7f8b2e": {
        "displayName": "Ronin7291",
        "externalPlatforms": [
            {
                "type": "xbl",
                "displayName": "Ronin7291"
            },
            {
                "type": "psn",
                "displayName": "Ronin7291"
            }
        ]
    },
    "c82647451867465684132f098d49fff9": {
        "displayName": "SWAMP IZZOO",
        "externalPlatforms": [
            {
                "type": "nintendo",
                "displayName": "SWAMP IZZOO"
            },
            {
                "type": "psn",
                "displayName": "SoixanteSoleils"
            }
        ]
    },
    "a4dbe7259cdd409aa957da06bb5091ad": {
        "displayName": "Boombabear99",
        "externalPlatforms": [
            {
                "type": "xbl",
                "displayName": "Boombabear99"
            },
            {
                "type": "steam",
                "displayName": "Boomba"
            }
        ]
    },
    "bba66d8ef8ae4e8e98613cb1fbdf99b7": {
        "displayName": "nxh-id-win",
        "externalPlatforms": [
            {
                "type": "xbl",
                "displayName": "acciocait"
            },
            {
                "type": "nintendo",
                "displayName": "nxh-id-win"
            }
        ]
    },
    "262b56b84f5f4d1e9e35aa27461b9e00": {
        "displayName": "SpiderDragoon27",
        "externalPlatforms": [
            {
                "type": "xbl",
                "displayName": "spiderdragoon27"
            }
        ]
    },
    "bde044dbd7bf43218156c3e530d4b0f3": {
        "displayName": "Pilotoprogranxd",
        "externalPlatforms": [
            {
                "type": "xbl",
                "displayName": "pilotoproxd"
            },
            {
                "type": "nintendo",
                "displayName": "Pilotoprogranxd"
            },
            {
                "type": "steam",
                "displayName": "pilotoprogranxd"
            },
            {
                "type": "psn",
                "displayName": "pilotoprogranxd"
            }
        ]
    },
    "957aeff5aaaa47a9b5aefd0b9f782219": {
        "displayName": "Travalion",
        "externalPlatforms": [
            {
                "type": "steam",
                "displayName": "Cuban Pete"
            }
        ]
    },
    "054c3898bdff4ebcaa38ba60dba24655": {
        "displayName": "Kuma9472",
        "externalPlatforms": [
            {
                "type": "xbl",
                "displayName": "KumaBear9472"
            },
            {
                "type": "nintendo",
                "displayName": "Kuma9472"
            },
            {
                "type": "psn",
                "displayName": "Kuma9472"
            }
        ]
    },
    "cf7006f4087342d28c394f31e53a1457": {
        "displayName": "King Flamingo 69",
        "externalPlatforms": [
            {
                "type": "xbl",
                "displayName": "MisterFlamingo6"
            },
            {
                "type": "steam",
                "displayName": "Peanus Butter"
            }
        ]
    },
    "01db5bbd29a84bb4a842551f6c4956bc": {
        "displayName": "SnowyzUwU",
        "externalPlatforms": [
            {
                "type": "xbl",
                "displayName": "SnowyzUwU"
            },
            {
                "type": "nintendo",
                "displayName": "SnowyzUwU"
            },
            {
                "type": "steam",
                "displayName": "SnowyzRevenge"
            },
            {
                "type": "psn",
                "displayName": "SnowyzUwU"
            }
        ]
    },
    "6f899200436f4ac983d2129310c188d1": {
        "displayName": "RawJuicyPotato",
        "externalPlatforms": [
            {
                "type": "steam",
                "displayName": "RawJuicyPotato"
            }
        ]
    },
    "e0a4189a9468405d8fa84dbc34a2baa6": {
        "displayName": "IKitty z",
        "externalPlatforms": [
            {
                "type": "xbl",
                "displayName": "lKitty lLover z"
            }
        ]
    },
    "18f18bd7129945cda42cc51522bc4d8d": {
        "displayName": "Winterstarf\u30f0",
        "externalPlatforms": [
            {
                "type": "xbl",
                "displayName": "Winterstarf"
            }
        ]
    },
    "1f3b64518ccc4a5fb405568285a25aec": {
        "displayName": "victyr.",
        "externalPlatforms": [
            {
                "type": "psn",
                "displayName": "PiThon-V"
            }
        ]
    },
    "dd93a87372ab46c28c719c743b1ab90f": {
        "displayName": "DropEmDeadd",
        "externalPlatforms": [
            {
                "type": "xbl",
                "displayName": "DropEmDeadd9516"
            },
            {
                "type": "nintendo",
                "displayName": "DropEmDeadd"
            }
        ]
    },
    "3a2930e1a54b4392bc3f2cd249c98dd5": {
        "displayName": "AlextanV",
        "externalPlatforms": [
            {
                "type": "psn",
                "displayName": "alextan12"
            }
        ]
    },
    "c7e6a17261234c89833994c138f646e7": {
        "displayName": "ItsyaboiiPJ",
        "externalPlatforms": [
            {
                "type": "xbl",
                "displayName": "ItsYaBoiiPJ"
            },
            {
                "type": "nintendo",
                "displayName": "ItsyaboiiPJ"
            },
            {
                "type": "steam",
                "displayName": "ItsYaBoiiPJ"
            },
            {
                "type": "psn",
                "displayName": "ItsYaBoiiPJ1030"
            }
        ]
    },
    "f147ad11d0cf4ef9a7a148d0c1d5b2dc": {
        "displayName": "V1C1NH0",
        "externalPlatforms": [
            {
                "type": "psn",
                "displayName": "zVictorLisboa"
            }
        ]
    },
    "a43bc1efbd6142608b0428a5a1e65234": {
        "displayName": "moonclassy",
        "externalPlatforms": [
            {
                "type": "nintendo",
                "displayName": "moonclassy"
            },
            {
                "type": "steam",
                "displayName": "moonclassy"
            }
        ]
    },
    "b3053f7c0f5143bf8d51e26f2e26ae15": {
        "displayName": "theus zb player",
        "externalPlatforms": [
            {
                "type": "xbl",
                "displayName": "TheuzinFn4118"
            },
            {
                "type": "psn",
                "displayName": "ItsRealTheus"
            }
        ]
    },
    "d8782c8c9725492794ba064bdd9586f5": {
        "displayName": "Alan \ufc5eWake",
        "externalPlatforms": [
            {
                "type": "xbl",
                "displayName": "LXavierW"
            },
            {
                "type": "nintendo",
                "displayName": "Alan \ufc5eWake"
            },
            {
                "type": "steam",
                "displayName": "LXavierW"
            },
            {
                "type": "psn",
                "displayName": "LXavierW"
            }
        ]
    },
    "ab259c3105104327a77189660444c85e": {
        "displayName": "jcrgameing101",
        "externalPlatforms": [
            {
                "type": "xbl",
                "displayName": "minecraftstyle8"
            },
            {
                "type": "nintendo",
                "displayName": "jcrgameing101"
            },
            {
                "type": "steam",
                "displayName": "JCRGAMEING101"
            }
        ]
    },
    "bd438d0995e24f939696ea2a3ea2595a": {
        "displayName": "\uff30\uff33\uff39\uff23\uff28\u00d8\uff33\uff29\uff33",
        "externalPlatforms": [
            {
                "type": "xbl",
                "displayName": "Abulato"
            }
        ]
    },
    "33a0b75a849240ac8cfbc15657c5dfac": {
        "displayName": "Lewis-.-1IQ",
        "externalPlatforms": [
            {
                "type": "xbl",
                "displayName": "Lewis20204"
            },
            {
                "type": "psn",
                "displayName": "Hewis-Poowis"
            }
        ]
    },
    "8eea62c7924a460491d96a88570d701b": {
        "displayName": "Kemking1987",
        "externalPlatforms": [
            {
                "type": "xbl",
                "displayName": "Kemking1987"
            },
            {
                "type": "psn",
                "displayName": "kemking1987"
            }
        ]
    },
    "f45f1d73ce2440bcbac71aa39438dc42": {
        "displayName": "AegisREDflector",
        "externalPlatforms": [
            {
                "type": "nintendo",
                "displayName": "AegisREDflector"
            },
            {
                "type": "psn",
                "displayName": "AegisREDflector"
            }
        ]
    },
    "163c19fbf1934c47aa4a59c59ce14c05": {
        "displayName": "UwUWeeWoo",
        "externalPlatforms": [
            {
                "type": "steam",
                "displayName": "Chazz"
            }
        ]
    },
    "251f39dace474a49a562d9e69eade717": {
        "displayName": "Squigglesquirel",
        "externalPlatforms": [
            {
                "type": "psn",
                "displayName": "squigglesquirel"
            }
        ]
    },
    "c00fb1de76024a0d8ded865e482212b2": {
        "displayName": "Gojos_Eyelashes",
        "externalPlatforms": [
            {
                "type": "nintendo",
                "displayName": "Gojos_Eyelashes"
            },
            {
                "type": "steam",
                "displayName": "Vistron"
            },
            {
                "type": "psn",
                "displayName": "Gojos_Eyelashes"
            }
        ]
    },
    "b8b76d1e954c4f97b2685aa2bccddf92": {
        "displayName": "Tokyst",
        "externalPlatforms": [
            {
                "type": "xbl",
                "displayName": "Zyst1307"
            }
        ]
    },
    "8d72145a68f74c2c8d44a70c2eb8840a": {
        "displayName": "SH-elx",
        "externalPlatforms": [
            {
                "type": "psn",
                "displayName": "elx"
            }
        ]
    },
    "734c812e91b44d3984d85b7dfcb34e38": {
        "displayName": "Afeda777",
        "externalPlatforms": [
            {
                "type": "xbl",
                "displayName": "Afeda777"
            },
            {
                "type": "nintendo",
                "displayName": "Afeda777"
            }
        ]
    },
    "67c4c472b7dd45b7be6803d0b21de964": {
        "displayName": "Heavellu",
        "externalPlatforms": []
    },
    "0a32801bce9b4569852a336b92f26255": {
        "displayName": "xQueenXena",
        "externalPlatforms": [
            {
                "type": "xbl",
                "displayName": "xQueenXena"
            }
        ]
    },
    "bb1acad73e5d410ea68d51f60a9de686": {
        "displayName": "BonFire135",
        "externalPlatforms": [
            {
                "type": "psn",
                "displayName": "BonFire5"
            }
        ]
    },
    "56440c5a4d2c4b5fa8fd42ef279c3873": {
        "displayName": "N\u0454iral",
        "externalPlatforms": [
            {
                "type": "steam",
                "displayName": "Neiral"
            }
        ]
    },
    "9475506eafbd40c191fde8400b2e88ca": {
        "displayName": "meekal66",
        "externalPlatforms": [
            {
                "type": "nintendo",
                "displayName": "meekal66"
            },
            {
                "type": "psn",
                "displayName": "meekal66"
            }
        ]
    },
    "bcc90bb1f8b34b0cb6cfc094bf77186d": {
        "displayName": "kazuhastoes",
        "externalPlatforms": [
            {
                "type": "xbl",
                "displayName": "SUNEATER9977"
            },
            {
                "type": "psn",
                "displayName": "kazuhastoes"
            }
        ]
    },
    "9668bd15a0804ba0bfa83f2606169b64": {
        "displayName": "Ko2aaak",
        "externalPlatforms": [
            {
                "type": "nintendo",
                "displayName": "Ko2aaak"
            },
            {
                "type": "psn",
                "displayName": "Ko2aaK2"
            }
        ]
    },
    "5dd0617bb5234da6aa2fddc2ec518a0b": {
        "displayName": "KanuPanther",
        "externalPlatforms": [
            {
                "type": "psn",
                "displayName": "KanuPanther"
            }
        ]
    },
    "1551e5360c1348e1a4a52a747444cb56": {
        "displayName": "AgreedCard8483",
        "externalPlatforms": [
            {
                "type": "nintendo",
                "displayName": "AgreedCard8483"
            }
        ]
    },
    "1e896aefb00440dfa018386777a5d0e0": {
        "displayName": "Adjustedleek010",
        "externalPlatforms": [
            {
                "type": "xbl",
                "displayName": "phatz010"
            }
        ]
    },
    "36787dec89924103b5ae5f6238723674": {
        "displayName": "SwiftyStardust",
        "externalPlatforms": [
            {
                "type": "nintendo",
                "displayName": "SwiftyStardust"
            },
            {
                "type": "psn",
                "displayName": "SwiftyStardust"
            }
        ]
    },
    "99205ab81ecc4fbebb8309f773de50a8": {
        "displayName": "breakfast7066",
        "externalPlatforms": [
            {
                "type": "xbl",
                "displayName": "breakfast7066"
            }
        ]
    },
    "65087abb85a54ec0bd3100a23c50dfd8": {
        "displayName": "Nikky100-",
        "externalPlatforms": [
            {
                "type": "psn",
                "displayName": "Nikkt1000"
            }
        ]
    },
    "5f036185c0364da1bc7e3b73cea75015": {
        "displayName": "Prisonedclash25",
        "externalPlatforms": [
            {
                "type": "xbl",
                "displayName": "PrisonedCLASH25"
            },
            {
                "type": "nintendo",
                "displayName": "Prisonedclash25"
            },
            {
                "type": "psn",
                "displayName": "ThanosVHS"
            }
        ]
    },
    "da857443db4e400191df40f5bf187ad9": {
        "displayName": "SagedPhoenix",
        "externalPlatforms": [
            {
                "type": "xbl",
                "displayName": "Shurropa"
            },
            {
                "type": "steam",
                "displayName": "Shurropa"
            },
            {
                "type": "psn",
                "displayName": "ItsShurropa"
            }
        ]
    },
    "b877e7d15a84414dbf133b45c812c1cc": {
        "displayName": "999 CC",
        "externalPlatforms": [
            {
                "type": "xbl",
                "displayName": "CCM123plays"
            },
            {
                "type": "nintendo",
                "displayName": "999 CC"
            },
            {
                "type": "psn",
                "displayName": "CCM123playz"
            }
        ]
    },
    "de8abd90531442408ac6442bf0a22f11": {
        "displayName": "PTG_Zero",
        "externalPlatforms": [
            {
                "type": "xbl",
                "displayName": "YeahBrad8420"
            },
            {
                "type": "nintendo",
                "displayName": "PTG_Zero"
            },
            {
                "type": "psn",
                "displayName": "Salt-_Shaker"
            }
        ]
    },
    "6247f55fd62140789fcaf3c6e5734f64": {
        "displayName": "BeastlyMudkip",
        "externalPlatforms": [
            {
                "type": "xbl",
                "displayName": "BeastlyMudkip"
            },
            {
                "type": "psn",
                "displayName": "BakedParmeSean"
            }
        ]
    },
    "e459bff2d7214d23ad185bf5012116ff": {
        "displayName": "UZl",
        "externalPlatforms": [
            {
                "type": "nintendo",
                "displayName": "UZl"
            }
        ]
    },
    "424c304f66094162a88fdd9ddfc557a1": {
        "displayName": "Jacobv40",
        "externalPlatforms": [
            {
                "type": "xbl",
                "displayName": "Jacobv23"
            },
            {
                "type": "psn",
                "displayName": "Jacobv40"
            }
        ]
    },
    "4b4e240a81a54ec0b5b7bde542aa382f": {
        "displayName": "PAVL\u00d3N",
        "externalPlatforms": [
            {
                "type": "xbl",
                "displayName": "PaVLoN3967"
            },
            {
                "type": "steam",
                "displayName": "PaVLoN"
            },
            {
                "type": "psn",
                "displayName": "PaVLoN256"
            }
        ]
    },
    "b4226e39ba444747b47b52af770ac931": {
        "displayName": "Zyontheroguee",
        "externalPlatforms": [
            {
                "type": "xbl",
                "displayName": "zyontherogue"
            }
        ]
    },
    "cd6e384440964669bf20976f72e81300": {
        "displayName": "iBor\u0268\u00f8_-",
        "externalPlatforms": [
            {
                "type": "xbl",
                "displayName": "iBorio4275"
            },
            {
                "type": "psn",
                "displayName": "iBorio-"
            }
        ]
    },
    "d9c59d58ce4b42389a5795200f32d912": {
        "displayName": "X1-Glitch-1X",
        "externalPlatforms": [
            {
                "type": "xbl",
                "displayName": "GlitchX1302"
            },
            {
                "type": "nintendo",
                "displayName": "X1-Glitch-1X"
            },
            {
                "type": "psn",
                "displayName": "X01-Glitch-01X"
            }
        ]
    },
    "c347c43b457e44e9898be8a0e6adb4fa": {
        "displayName": "\u8679\u30d1\u30f3\u30d7\u30ad\u30f3",
        "externalPlatforms": [
            {
                "type": "nintendo",
                "displayName": "\u8679\u30d1\u30f3\u30d7\u30ad\u30f3"
            },
            {
                "type": "psn",
                "displayName": "NIJIpumpkin"
            }
        ]
    },
    "bd51edb2fb3e4e4fb853aecdf6019a16": {
        "displayName": "DeathTrooper435",
        "externalPlatforms": [
            {
                "type": "xbl",
                "displayName": "DeathTrooper435"
            },
            {
                "type": "psn",
                "displayName": "DeathTrooper2099"
            }
        ]
    },
    "f3c8200279be4654b748bf992a4c902b": {
        "displayName": "Knoctiv",
        "externalPlatforms": [
            {
                "type": "psn",
                "displayName": "Knoctiv"
            }
        ]
    },
    "cbb0d17cfe2f4708b6738571a4cec72c": {
        "displayName": "XxBoi101xX",
        "externalPlatforms": [
            {
                "type": "xbl",
                "displayName": "Spax Shark"
            }
        ]
    },
    "b4e2b468b8c0437e810a1c53897c2b6c": {
        "displayName": "Kokichi233",
        "externalPlatforms": [
            {
                "type": "psn",
                "displayName": "Kokichi233"
            }
        ]
    },
    "726a592a7ac2454ebed69bb67fbdf39f": {
        "displayName": "theLourzax",
        "externalPlatforms": [
            {
                "type": "nintendo",
                "displayName": "theLourzax"
            },
            {
                "type": "psn",
                "displayName": "theLourzax"
            }
        ]
    },
    "95be7db0a2a54c90ada38d3dbbe50808": {
        "displayName": "Ms.Angel \u029a\u0457\u025e",
        "externalPlatforms": [
            {
                "type": "psn",
                "displayName": "eliteeangel_"
            }
        ]
    },
    "012b0e14d00540dea6764d2248c3d9d1": {
        "displayName": "b4byCJ",
        "externalPlatforms": [
            {
                "type": "psn",
                "displayName": "babyburch33"
            }
        ]
    },
    "98130f0f864741c79e61cf394f61dd73": {
        "displayName": "Art of Kimchi",
        "externalPlatforms": [
            {
                "type": "xbl",
                "displayName": "Kimchi Rx"
            }
        ]
    },
    "4042007215c1416da4a65290a3ddb70a": {
        "displayName": "BuySharp",
        "externalPlatforms": [
            {
                "type": "xbl",
                "displayName": "SendTheZens"
            },
            {
                "type": "nintendo",
                "displayName": "BuySharp"
            }
        ]
    },
    "81b9d61cab714e039e969a96e72d2f79": {
        "displayName": "SICKDASLICK",
        "externalPlatforms": [
            {
                "type": "xbl",
                "displayName": "SICKDASLICK"
            },
            {
                "type": "steam",
                "displayName": "SICKDASLICK"
            },
            {
                "type": "psn",
                "displayName": "SICKDASLICK"
            }
        ]
    },
    "cd846a08e11946d6a6c5f2acbefaf7f4": {
        "displayName": "KCPRIMAL2",
        "externalPlatforms": [
            {
                "type": "xbl",
                "displayName": "KC PRIMAL 2"
            },
            {
                "type": "nintendo",
                "displayName": "KCPRIMAL2"
            }
        ]
    },
    "8449814756844fc9b4be218adfd793aa": {
        "displayName": "King_Riott",
        "externalPlatforms": [
            {
                "type": "nintendo",
                "displayName": "King_Riott"
            }
        ]
    },
    "11e017f59579482393040c80e7ad89b1": {
        "displayName": "Roodee",
        "externalPlatforms": [
            {
                "type": "steam",
                "displayName": "Roodee"
            }
        ]
    },
    "2208cacdf4ca432696201d1a72c93c3f": {
        "displayName": "DarksWifey",
        "externalPlatforms": [
            {
                "type": "xbl",
                "displayName": "Sugarr mamii"
            },
            {
                "type": "nintendo",
                "displayName": "DarksWifey"
            },
            {
                "type": "psn",
                "displayName": "CrysisLuvr"
            }
        ]
    },
    "315ab98f23f0478eb3570752cf7a88a8": {
        "displayName": "kaptkronic420",
        "externalPlatforms": [
            {
                "type": "xbl",
                "displayName": "Kaptkronic2698"
            },
            {
                "type": "nintendo",
                "displayName": "kaptkronic420"
            },
            {
                "type": "steam",
                "displayName": "Kapt.Kronic"
            },
            {
                "type": "psn",
                "displayName": "Kapt_Kronic420"
            }
        ]
    },
    "b2b1d277bb6d4fa08178a309e5c562a2": {
        "displayName": "EPJayumu",
        "externalPlatforms": [
            {
                "type": "nintendo",
                "displayName": "EPJayumu"
            }
        ]
    },
    "9c015e49b4a3470b8ba10be599dac994": {
        "displayName": "FuriousFijian",
        "externalPlatforms": [
            {
                "type": "nintendo",
                "displayName": "FuriousFijian"
            },
            {
                "type": "psn",
                "displayName": "FuriousFijian"
            }
        ]
    },
    "64ebe617c51445549004b825d0d8d7fe": {
        "displayName": "LeYdarb",
        "externalPlatforms": [
            {
                "type": "xbl",
                "displayName": "LeYdarb"
            },
            {
                "type": "nintendo",
                "displayName": "LeYdarb"
            },
            {
                "type": "steam",
                "displayName": "Brady"
            },
            {
                "type": "psn",
                "displayName": "StinkyYdarb"
            }
        ]
    },
    "6153ec86f320461c90f49cd63a623ce2": {
        "displayName": "misty mauve",
        "externalPlatforms": [
            {
                "type": "psn",
                "displayName": "misty mauve"
            }
        ]
    },
    "a4b6d2f47e96480e991eb06fef322f01": {
        "displayName": "aidynmarie7309",
        "externalPlatforms": [
            {
                "type": "xbl",
                "displayName": "aidynmarie7309"
            }
        ]
    },
    "debbab68f9d642d391a7cb8a131d59ae": {
        "displayName": "Fumbles6985",
        "externalPlatforms": [
            {
                "type": "psn",
                "displayName": "Fumbles6985"
            }
        ]
    },
    "92db344bda394fa7b3fd547e577a11be": {
        "displayName": "CPTN.Dadpool",
        "externalPlatforms": [
            {
                "type": "xbl",
                "displayName": "CPTNxDadpool"
            },
            {
                "type": "nintendo",
                "displayName": "CPTN.Dadpool"
            },
            {
                "type": "psn",
                "displayName": "CPTN-dadpool"
            }
        ]
    },
    "d942ed314a8840d9be98c067c27133d0": {
        "displayName": "PERUNAMUUUUUUUSI",
        "externalPlatforms": [
            {
                "type": "xbl",
                "displayName": "miccixmax"
            },
            {
                "type": "nintendo",
                "displayName": "PERUNAMUUUUUUUSI"
            },
            {
                "type": "psn",
                "displayName": "miccixmax"
            }
        ]
    },
    "d054f151861240f299d0c1fa707a41f2": {
        "displayName": "Dualpistol66",
        "externalPlatforms": [
            {
                "type": "xbl",
                "displayName": "Buttercup6566"
            },
            {
                "type": "nintendo",
                "displayName": "Dualpistol66"
            }
        ]
    },
    "320f93e082de4004bd54a20f984d5ac2": {
        "displayName": "SnipezKierz",
        "externalPlatforms": [
            {
                "type": "psn",
                "displayName": "SnipezKierzz"
            }
        ]
    },
    "2ce57340352f415280863e2686e5c201": {
        "displayName": "WeGoAGANE",
        "externalPlatforms": [
            {
                "type": "psn",
                "displayName": "angelxa0105"
            }
        ]
    },
    "41bc15e1177942b9a17d6f50334a92be": {
        "displayName": "Tyton_hayes",
        "externalPlatforms": [
            {
                "type": "psn",
                "displayName": "Zyon-_-999"
            }
        ]
    },
    "9cb0858d8d40468d9755fc8618169a19": {
        "displayName": "Skibidi Helsie",
        "externalPlatforms": [
            {
                "type": "xbl",
                "displayName": "RetroRed5668"
            },
            {
                "type": "nintendo",
                "displayName": "Skibidi Helsie"
            },
            {
                "type": "steam",
                "displayName": "jug"
            },
            {
                "type": "psn",
                "displayName": "RetroRed64"
            }
        ]
    },
    "2e0cc5c008dc4accb863328dd0fa3fde": {
        "displayName": "Hotmommas12",
        "externalPlatforms": [
            {
                "type": "psn",
                "displayName": "ChorizoNJarrito8"
            }
        ]
    },
    "17b93474db834b8595208f5694784fc7": {
        "displayName": "MAZTUHMIND",
        "externalPlatforms": [
            {
                "type": "psn",
                "displayName": "MAZTUHMIND"
            }
        ]
    },
    "280cebd4583f4b7aa160db908648f16c": {
        "displayName": "HotHead4267",
        "externalPlatforms": [
            {
                "type": "xbl",
                "displayName": "HotHead4267"
            }
        ]
    },
    "166cbcadd2ec4b2cb2b5ba5359a3b8a6": {
        "displayName": "Bam-PandaMan",
        "externalPlatforms": [
            {
                "type": "psn",
                "displayName": "CouchCushion13"
            }
        ]
    },
    "70f0a8359db74a1aa1c149def20a43b8": {
        "displayName": "User-676c475fe4",
        "externalPlatforms": [
            {
                "type": "psn",
                "displayName": "Frizzzdome"
            }
        ]
    },
    "255ca3f595ef4886b79dc65c3f9c243b": {
        "displayName": "pickleman73",
        "externalPlatforms": [
            {
                "type": "psn",
                "displayName": "pickleman73"
            }
        ]
    },
    "137fe06a6ea74e23969259642d853594": {
        "displayName": "LeUsagi",
        "externalPlatforms": [
            {
                "type": "xbl",
                "displayName": "LeUsagii"
            },
            {
                "type": "nintendo",
                "displayName": "LeUsagi"
            },
            {
                "type": "steam",
                "displayName": "Inkzxc"
            }
        ]
    },
    "06fa7162e7324389bfbd0a025ff82fdb": {
        "displayName": "JJFNAF_FORTNITE1",
        "externalPlatforms": [
            {
                "type": "psn",
                "displayName": "JJFNAF_FORTNITE1"
            }
        ]
    },
    "5b218a0675794a24b2831d80d8bfdbf3": {
        "displayName": "APtony_",
        "externalPlatforms": [
            {
                "type": "xbl",
                "displayName": "APtony415"
            },
            {
                "type": "nintendo",
                "displayName": "APtony_"
            }
        ]
    },
    "5339e15d9e2143559ba32c3377359c15": {
        "displayName": "Martin80125",
        "externalPlatforms": [
            {
                "type": "nintendo",
                "displayName": "Martin80125"
            },
            {
                "type": "steam",
                "displayName": "1+1"
            },
            {
                "type": "psn",
                "displayName": "L2Skies"
            }
        ]
    },
    "7616507142a147ee963535728ff748c8": {
        "displayName": "\u7136 mutant \u30c4 \u03a8",
        "externalPlatforms": [
            {
                "type": "nintendo",
                "displayName": "\u7136 mutant \u30c4 \u03a8"
            },
            {
                "type": "steam",
                "displayName": "mutant"
            }
        ]
    },
    "aa95d3bc9d0b4bac8d52f1f4c70ecfe0": {
        "displayName": "ThomasTusk",
        "externalPlatforms": [
            {
                "type": "xbl",
                "displayName": "ThomasTusk"
            },
            {
                "type": "psn",
                "displayName": "ThomasTusk"
            }
        ]
    },
    "62ee88ff47584ba1bda63876cdfc3bd5": {
        "displayName": "FrostyChains",
        "externalPlatforms": [
            {
                "type": "xbl",
                "displayName": "Fr0styCh4ins"
            },
            {
                "type": "steam",
                "displayName": "FrostyChains"
            }
        ]
    },
    "3baa61ba27094b7ba8f4f9735ab23a01": {
        "displayName": "CMoneySquad_24",
        "externalPlatforms": [
            {
                "type": "psn",
                "displayName": "CMoneySquad_24"
            }
        ]
    },
    "3c52c24cae1349518f4575ae310cf42b": {
        "displayName": "TTV_BLOODZ2024",
        "externalPlatforms": [
            {
                "type": "xbl",
                "displayName": "TTVBLOODZ24"
            }
        ]
    }
}