{
    "f83d283bd20940688134c2f2d6c20ed6": {
        "displayName": "ZEROHUNTER44",
        "externalPlatforms": [
            {
                "type": "psn",
                "displayName": "AOF-ZEROHUNTER"
            }
        ]
    },
    "6f8ba442daf14601b392aabee672b7ca": {
        "displayName": "chekenwangs",
        "externalPlatforms": [
            {
                "type": "xbl",
                "displayName": "chekenwangs"
            },
            {
                "type": "nintendo",
                "displayName": "chekenwangs"
            }
        ]
    },
    "ce5ae2b562344756927f70485610f3ff": {
        "displayName": "n\ufc5eaughty boy",
        "externalPlatforms": [
            {
                "type": "psn",
                "displayName": "tenchiYT"
            }
        ]
    },
    "7b13c08ed65c477db0e9c5fabfa3d3e2": {
        "displayName": "VincentWeir\u1d40\u1d40\u2c7d",
        "externalPlatforms": [
            {
                "type": "xbl",
                "displayName": "VincentWeir"
            },
            {
                "type": "nintendo",
                "displayName": "VincentWeir\u1d40\u1d40\u2c7d"
            }
        ]
    },
    "521d656413ab49829b35c16dafb0a726": {
        "displayName": "Moneybagg Yo 21",
        "externalPlatforms": [
            {
                "type": "xbl",
                "displayName": "the hulkster 21"
            },
            {
                "type": "nintendo",
                "displayName": "Moneybagg Yo 21"
            }
        ]
    },
    "84c071f4cb4d4beb9e4cb513058c1c28": {
        "displayName": "Boi_Bloofin",
        "externalPlatforms": [
            {
                "type": "xbl",
                "displayName": "yourboibloofin"
            },
            {
                "type": "nintendo",
                "displayName": "Boi_Bloofin"
            },
            {
                "type": "psn",
                "displayName": "Boi_Bloofin_YT"
            }
        ]
    },
    "1e41b9d32d8945ebbe359892f67b82da": {
        "displayName": "Sballas",
        "externalPlatforms": [
            {
                "type": "nintendo",
                "displayName": "Sballas"
            },
            {
                "type": "steam",
                "displayName": "Kay"
            },
            {
                "type": "psn",
                "displayName": "sultan-rocks"
            }
        ]
    },
    "ca2e2e46173c4969b81f2cdfecbbcbb5": {
        "displayName": "PotentialPoob",
        "externalPlatforms": [
            {
                "type": "xbl",
                "displayName": "PotentPoob"
            },
            {
                "type": "psn",
                "displayName": "PotentBoop"
            }
        ]
    },
    "4523627704d84654830cdcd9612022f8": {
        "displayName": "AxellGamer9053",
        "externalPlatforms": [
            {
                "type": "xbl",
                "displayName": "Axell Gamer9053"
            }
        ]
    },
    "e7ffdec0710b4c7fa55828213cc2a440": {
        "displayName": "EriChaosYT",
        "externalPlatforms": [
            {
                "type": "xbl",
                "displayName": "EriChaos"
            },
            {
                "type": "nintendo",
                "displayName": "EriChaosYT"
            },
            {
                "type": "psn",
                "displayName": "EriChaosYT"
            }
        ]
    },
    "6af0e6fc482447f3b0f198c9f6f6e31a": {
        "displayName": "DfinitiveDfalt",
        "externalPlatforms": [
            {
                "type": "nintendo",
                "displayName": "DfinitiveDfalt"
            },
            {
                "type": "steam",
                "displayName": "Definitive"
            }
        ]
    },
    "67c40ecf176f45c9ab0bb7561d7781ea": {
        "displayName": "Marky UwU",
        "externalPlatforms": [
            {
                "type": "xbl",
                "displayName": "Marky 0w0"
            }
        ]
    },
    "909644230ae04b529661b05de1b1b33a": {
        "displayName": "DCWMario",
        "externalPlatforms": [
            {
                "type": "xbl",
                "displayName": "DCWMario"
            },
            {
                "type": "nintendo",
                "displayName": "DCWMario"
            },
            {
                "type": "steam",
                "displayName": "DCWMario"
            }
        ]
    },
    "9adc941e49094a63a91651beb61656a4": {
        "displayName": "Temptress_7",
        "externalPlatforms": [
            {
                "type": "psn",
                "displayName": "TeMpTrEsS_7"
            }
        ]
    },
    "c1b7be6033ee432789330627bf9535ad": {
        "displayName": "\uff21\uff54\uff4f\uff4d\uff49\uff43",
        "externalPlatforms": [
            {
                "type": "xbl",
                "displayName": "AtomicSW1952"
            },
            {
                "type": "nintendo",
                "displayName": "\uff21\uff54\uff4f\uff4d\uff49\uff43"
            },
            {
                "type": "steam",
                "displayName": "AtomicSW"
            },
            {
                "type": "psn",
                "displayName": "AtomicSW"
            }
        ]
    },
    "e141aa00873e47169d02746e890fb5b3": {
        "displayName": "CarnageKiller9",
        "externalPlatforms": [
            {
                "type": "xbl",
                "displayName": "CarnageKiller9"
            },
            {
                "type": "nintendo",
                "displayName": "CarnageKiller9"
            },
            {
                "type": "psn",
                "displayName": "Serbidian"
            }
        ]
    },
    "345e46fd54794632b941206f31bd38b5": {
        "displayName": "DeadwoodWasHere",
        "externalPlatforms": [
            {
                "type": "xbl",
                "displayName": "DeadwoodWasHere"
            },
            {
                "type": "psn",
                "displayName": "heyitsderpify"
            }
        ]
    },
    "3294a90729284ab98f9e885fd6a6507d": {
        "displayName": "XtremeRattlehead",
        "externalPlatforms": [
            {
                "type": "xbl",
                "displayName": "Agent Thrash777"
            },
            {
                "type": "nintendo",
                "displayName": "XtremeRattlehead"
            },
            {
                "type": "steam",
                "displayName": "Xtremerattlehead"
            }
        ]
    },
    "d2516b343708473a8fdb36122764d53c": {
        "displayName": "mannequinlove",
        "externalPlatforms": [
            {
                "type": "psn",
                "displayName": "plxnisphere"
            }
        ]
    },
    "91733ac8636c451598bd50ac0993433b": {
        "displayName": "Robotothekilla",
        "externalPlatforms": [
            {
                "type": "psn",
                "displayName": "RobotoTheKillA"
            }
        ]
    },
    "379373f5418745b8b8abacf0a89c9b2f": {
        "displayName": "SharkWarrior449",
        "externalPlatforms": [
            {
                "type": "nintendo",
                "displayName": "SharkWarrior449"
            }
        ]
    },
    "9f01e36556754fd591ff3177c5aa48d3": {
        "displayName": "SylvieKitty",
        "externalPlatforms": [
            {
                "type": "xbl",
                "displayName": "SylvieKitty"
            }
        ]
    },
    "6b4b056b56d5426e828be65a76451622": {
        "displayName": "Vibez778",
        "externalPlatforms": [
            {
                "type": "psn",
                "displayName": "Vibez69420"
            }
        ]
    },
    "91567a92711d467ba622c68567b1374d": {
        "displayName": "I\u0430n -_-",
        "externalPlatforms": [
            {
                "type": "nintendo",
                "displayName": "I\u0430n -_-"
            },
            {
                "type": "steam",
                "displayName": "Derek (original)"
            },
            {
                "type": "psn",
                "displayName": "Dereklind77"
            }
        ]
    },
    "9477f4abf02d4abb82b5819fe8d2c1de": {
        "displayName": "rickythebobbyy",
        "externalPlatforms": [
            {
                "type": "steam",
                "displayName": "rickythebobbyy"
            },
            {
                "type": "psn",
                "displayName": "rickythebobbyy"
            }
        ]
    },
    "ac2929a88a034fd68a79be3fcf199850": {
        "displayName": "Coffeeky",
        "externalPlatforms": [
            {
                "type": "xbl",
                "displayName": "Coffeeky4922"
            },
            {
                "type": "psn",
                "displayName": "duskjj"
            }
        ]
    },
    "a873d854b22a442b992839c8d229b2ca": {
        "displayName": "AssassinKid2400",
        "externalPlatforms": [
            {
                "type": "xbl",
                "displayName": "LetsSkoden2"
            },
            {
                "type": "nintendo",
                "displayName": "AssassinKid2400"
            },
            {
                "type": "psn",
                "displayName": "GhostTeen240"
            }
        ]
    },
    "5c78d886d7114901851c29cb6faa5e31": {
        "displayName": "wzoah",
        "externalPlatforms": [
            {
                "type": "steam",
                "displayName": "sadiemrogerss"
            },
            {
                "type": "psn",
                "displayName": "wzoah"
            }
        ]
    },
    "78e22ca5e9544d199ada2cb4127c96df": {
        "displayName": "QuestEnjoyer",
        "externalPlatforms": [
            {
                "type": "psn",
                "displayName": "njbes_"
            }
        ]
    },
    "4cb966b22cc64f569f240262ceee4fc9": {
        "displayName": "octoboy1",
        "externalPlatforms": [
            {
                "type": "xbl",
                "displayName": "BunnyMaster4031"
            },
            {
                "type": "nintendo",
                "displayName": "$hmac-sha256$keyId=1$5Ox3cBUBh5KRI3ksz9g4j98alH5eV38h+Idt85/wpO4"
            }
        ]
    },
    "0477035a85e94548a045f8a821549206": {
        "displayName": "Kenny2fresh2",
        "externalPlatforms": [
            {
                "type": "psn",
                "displayName": "kenny2fresh725"
            }
        ]
    },
    "494777c866f045c691f94320b24a8ca2": {
        "displayName": "loadedpotato_",
        "externalPlatforms": [
            {
                "type": "psn",
                "displayName": "vital-space-_"
            }
        ]
    },
    "dd8fb6af4177410fab9d73e9f7be0037": {
        "displayName": "Peter Pusheen",
        "externalPlatforms": [
            {
                "type": "xbl",
                "displayName": "PeterPusheen"
            },
            {
                "type": "steam",
                "displayName": "Aerith's Husband"
            },
            {
                "type": "psn",
                "displayName": "ShinPusheen"
            }
        ]
    },
    "913545881435452fb31082ff812d5a3b": {
        "displayName": "poppetscales",
        "externalPlatforms": [
            {
                "type": "psn",
                "displayName": "Paigeeypoodle18"
            }
        ]
    },
    "83e9ebed77b94b3bb63fa65a481cbaa4": {
        "displayName": "Dax UwU",
        "externalPlatforms": [
            {
                "type": "xbl",
                "displayName": "Daxcool100"
            },
            {
                "type": "nintendo",
                "displayName": "Dax UwU"
            },
            {
                "type": "steam",
                "displayName": "Daxy"
            },
            {
                "type": "psn",
                "displayName": "DaxTheWeirdo"
            }
        ]
    },
    "6920595795b04a9697733c958b363f15": {
        "displayName": "ChrisRob19",
        "externalPlatforms": [
            {
                "type": "xbl",
                "displayName": "AalbinRL"
            },
            {
                "type": "nintendo",
                "displayName": "ChrisRob19"
            }
        ]
    },
    "9ee51751211744c4bf463fe9133b8774": {
        "displayName": "Azuurav",
        "externalPlatforms": [
            {
                "type": "steam",
                "displayName": "Azuurav"
            }
        ]
    },
    "0250a9f1a62a4916afe2a9ae5182e776": {
        "displayName": "HitEmUp_Draq",
        "externalPlatforms": [
            {
                "type": "psn",
                "displayName": "HitEmUp_Draq"
            }
        ]
    },
    "2ba122a6a0524966b7cd3f45b46b92bd": {
        "displayName": "TheEliminator36",
        "externalPlatforms": [
            {
                "type": "xbl",
                "displayName": "TheEliminator36"
            }
        ]
    },
    "ce4dc3c0cf4d459294375f73ed3ef8c4": {
        "displayName": "dankganronpa",
        "externalPlatforms": [
            {
                "type": "xbl",
                "displayName": "dankganronpa"
            },
            {
                "type": "nintendo",
                "displayName": "dankganronpa"
            },
            {
                "type": "psn",
                "displayName": "dankganronpa"
            }
        ]
    },
    "8111c052cf8c4802a00f0f48a88c721d": {
        "displayName": "darkfox.1",
        "externalPlatforms": [
            {
                "type": "nintendo",
                "displayName": "darkfox.1"
            },
            {
                "type": "steam",
                "displayName": "darkfox"
            }
        ]
    },
    "4237e673edec4456b9d95aaadfaa396e": {
        "displayName": "GlizzyBLM",
        "externalPlatforms": [
            {
                "type": "xbl",
                "displayName": "oogavin1"
            }
        ]
    },
    "71baf8b93dbe4202988e1f983fe20e2f": {
        "displayName": "YTRich",
        "externalPlatforms": [
            {
                "type": "xbl",
                "displayName": "RichM YT"
            },
            {
                "type": "nintendo",
                "displayName": "YTRich"
            }
        ]
    },
    "691f3392241e4eacbe575502a5b452ca": {
        "displayName": "ZB \u3057\u3065\u304d\u3063\u3061",
        "externalPlatforms": [
            {
                "type": "psn",
                "displayName": "ZBFV_Shizuki-YT"
            }
        ]
    },
    "89bdcef06dd64abd9bd0906f5d3f9951": {
        "displayName": "uhDaark",
        "externalPlatforms": [
            {
                "type": "psn",
                "displayName": "uhDaark"
            }
        ]
    },
    "4116930e650a42bea42c356327f54fe8": {
        "displayName": "SHARKIE_18_BOI",
        "externalPlatforms": [
            {
                "type": "xbl",
                "displayName": "IrateDesert8674"
            },
            {
                "type": "psn",
                "displayName": "BlindSide_jack"
            }
        ]
    },
    "6b65bf3982ef491e9fdd6c748bad6010": {
        "displayName": "Esrev_",
        "externalPlatforms": [
            {
                "type": "xbl",
                "displayName": "Versatile1223"
            },
            {
                "type": "nintendo",
                "displayName": "Esrev_"
            },
            {
                "type": "steam",
                "displayName": "\u2666\u2666\u2666VersatileGaming\u2666\u2666"
            },
            {
                "type": "psn",
                "displayName": "Versatile_77"
            }
        ]
    },
    "d2cc6a80782745389ab00929beaf46d8": {
        "displayName": "oiRiEiDio",
        "externalPlatforms": [
            {
                "type": "psn",
                "displayName": "oiRiEiDio"
            }
        ]
    },
    "26801d9328b04335b8d1eb57a35416db": {
        "displayName": "juliushero15",
        "externalPlatforms": [
            {
                "type": "xbl",
                "displayName": "ILoveGH85"
            }
        ]
    },
    "01bbdeea8e45455a8f93c9d6df49d5df": {
        "displayName": "HalfAnimal72",
        "externalPlatforms": [
            {
                "type": "xbl",
                "displayName": "HalfAnimal72"
            },
            {
                "type": "nintendo",
                "displayName": "HalfAnimal72"
            },
            {
                "type": "steam",
                "displayName": "presdog07"
            },
            {
                "type": "psn",
                "displayName": "Halfanimal72"
            }
        ]
    },
    "4ebf85d1e9cd474389a07142a3d43c8c": {
        "displayName": "DragonJelly0",
        "externalPlatforms": [
            {
                "type": "xbl",
                "displayName": "DragonJelly0"
            }
        ]
    },
    "49b3891bc932421382ee0c70053478b1": {
        "displayName": "l3w1smc04",
        "externalPlatforms": [
            {
                "type": "xbl",
                "displayName": "AldiBagFor5p"
            },
            {
                "type": "nintendo",
                "displayName": "l3w1smc04"
            },
            {
                "type": "psn",
                "displayName": "chubbywalrus420"
            }
        ]
    },
    "e2c27520eaf4426788e8b4e8c2e02993": {
        "displayName": "\u0405\u0430rge",
        "externalPlatforms": [
            {
                "type": "xbl",
                "displayName": "asfdec"
            }
        ]
    },
    "199e6db8791f4b2c887fd9326c9afc77": {
        "displayName": "MarIuxiaa",
        "externalPlatforms": [
            {
                "type": "nintendo",
                "displayName": "MarIuxiaa"
            },
            {
                "type": "psn",
                "displayName": "MarIuxiaaa"
            }
        ]
    },
    "d2a847a02f294d5ca318442bc0d3d894": {
        "displayName": "Cornelius_the1st",
        "externalPlatforms": [
            {
                "type": "psn",
                "displayName": "Saul__Goodman1"
            }
        ]
    },
    "afb6cda80ac642889b93754c3a988e0f": {
        "displayName": "LoudPakk27",
        "externalPlatforms": []
    },
    "fb9ad83ec8fc41528772067372bd9a3d": {
        "displayName": "Pandaluver25",
        "externalPlatforms": [
            {
                "type": "nintendo",
                "displayName": "Pandaluver25"
            },
            {
                "type": "psn",
                "displayName": "PandaLuver25"
            }
        ]
    },
    "e3fb5f21d9eb4e0e8ee1808e6377252c": {
        "displayName": "Loahner",
        "externalPlatforms": [
            {
                "type": "steam",
                "displayName": "LonelyLoner"
            },
            {
                "type": "psn",
                "displayName": "HP_Daybreak_94"
            }
        ]
    },
    "7ed525e2f14a43faae44b10e1fe769a6": {
        "displayName": "xxanotheron2121",
        "externalPlatforms": [
            {
                "type": "xbl",
                "displayName": "xxanotheron21"
            },
            {
                "type": "nintendo",
                "displayName": "xxanotheron2121"
            }
        ]
    },
    "6111140a96d0485cbd124cb8938be6db": {
        "displayName": "Steel Wool Foox.",
        "externalPlatforms": [
            {
                "type": "xbl",
                "displayName": "SlipKnotF0ox"
            },
            {
                "type": "psn",
                "displayName": "Gh0stlyF0ox"
            }
        ]
    },
    "c375f79e197a416e88515cbf86348d06": {
        "displayName": "infinitepancakes",
        "externalPlatforms": [
            {
                "type": "nintendo",
                "displayName": "infinitepancakes"
            },
            {
                "type": "psn",
                "displayName": "InfinitePancake"
            }
        ]
    },
    "d0e1149391764e589b2ebc01e16b96c1": {
        "displayName": "EatYeetYes5586",
        "externalPlatforms": [
            {
                "type": "xbl",
                "displayName": "EatYeetYes5586"
            }
        ]
    },
    "471e1a8ddbed4f7f89057ea969ee6375": {
        "displayName": "Bastia3478",
        "externalPlatforms": [
            {
                "type": "psn",
                "displayName": "Bastia047"
            }
        ]
    },
    "0744c56f7490470eb0b4720d60509942": {
        "displayName": "MyaTheKyd",
        "externalPlatforms": [
            {
                "type": "psn",
                "displayName": "MyaTheKyd"
            }
        ]
    },
    "cddd1a7e8d16485f94aef6fd2e530081": {
        "displayName": "BOSS x Hazardz",
        "externalPlatforms": [
            {
                "type": "xbl",
                "displayName": "BOSS x Hazardz"
            }
        ]
    },
    "9b51a7c657b849d4b7172d1f645e1435": {
        "displayName": "unokitty",
        "externalPlatforms": [
            {
                "type": "xbl",
                "displayName": "unokitty"
            }
        ]
    },
    "6c075cc89bbd417ebb3f9449a75d64ca": {
        "displayName": "Juicie_",
        "externalPlatforms": [
            {
                "type": "xbl",
                "displayName": "Juicie8505"
            },
            {
                "type": "nintendo",
                "displayName": "Juicie_"
            },
            {
                "type": "steam",
                "displayName": "Roka"
            }
        ]
    },
    "dde0be195c7d4c47a5fe15e41334dfb8": {
        "displayName": "User-35081d7870",
        "externalPlatforms": [
            {
                "type": "nintendo",
                "displayName": "User-35081d7870"
            }
        ]
    },
    "882765dc6dff41e6afa59d97c67734ba": {
        "displayName": "Apawlow",
        "externalPlatforms": [
            {
                "type": "nintendo",
                "displayName": "Apawlow"
            },
            {
                "type": "steam",
                "displayName": "Apawlow"
            },
            {
                "type": "psn",
                "displayName": "Apawlow"
            }
        ]
    },
    "22e411eade6641dc845bf6ba7c082d6e": {
        "displayName": "Ddraig817",
        "externalPlatforms": [
            {
                "type": "nintendo",
                "displayName": "Ddraig817"
            },
            {
                "type": "steam",
                "displayName": "Ddraig817"
            },
            {
                "type": "psn",
                "displayName": "Ddraig_Lord817"
            }
        ]
    },
    "789a8414b0af442eb43bd74e1a79dff5": {
        "displayName": "Vitality2423",
        "externalPlatforms": [
            {
                "type": "xbl",
                "displayName": "Vitality2423"
            },
            {
                "type": "steam",
                "displayName": "Vitality"
            },
            {
                "type": "psn",
                "displayName": "FsS_Vitality"
            }
        ]
    },
    "964823aa01d540718da280f6c1184a29": {
        "displayName": "bulldogzach",
        "externalPlatforms": [
            {
                "type": "nintendo",
                "displayName": "bulldogzach"
            },
            {
                "type": "psn",
                "displayName": "bulldogzach"
            }
        ]
    },
    "7bc60ea7b21a42feb716c894c243b656": {
        "displayName": "Leon Beatle",
        "externalPlatforms": [
            {
                "type": "xbl",
                "displayName": "Leon Beatle"
            },
            {
                "type": "nintendo",
                "displayName": "Leon Beatle"
            }
        ]
    },
    "8161736436f24c7a9e8c55d82d4a1ea3": {
        "displayName": "doktor segs",
        "externalPlatforms": [
            {
                "type": "nintendo",
                "displayName": "doktor segs"
            },
            {
                "type": "steam",
                "displayName": "joe"
            }
        ]
    },
    "5f9d8c5d384743fda6cdb7f6321d8d9a": {
        "displayName": "Me0nii",
        "externalPlatforms": [
            {
                "type": "xbl",
                "displayName": "Me0nii"
            },
            {
                "type": "steam",
                "displayName": "NightlyIceMeltr"
            }
        ]
    },
    "570db20b36464b6db2454e2706aeeb23": {
        "displayName": "pooolb",
        "externalPlatforms": [
            {
                "type": "nintendo",
                "displayName": "$hmac-sha256$keyId=1$5Ox3cBUBh5KRI3ksz9g4j98alH5eV38h+Idt85/wpO4"
            }
        ]
    },
    "7bb11c97a1824f1a9586d5b396c49b71": {
        "displayName": "Weeaveer",
        "externalPlatforms": [
            {
                "type": "xbl",
                "displayName": "I Love Angel374"
            },
            {
                "type": "steam",
                "displayName": "Weaver"
            },
            {
                "type": "psn",
                "displayName": "Grigori_Weaver_"
            }
        ]
    },
    "1cf9b58fe7c04437b3224b721179f6ce": {
        "displayName": "Alien_Gono",
        "externalPlatforms": [
            {
                "type": "xbl",
                "displayName": "Alien Gono"
            },
            {
                "type": "nintendo",
                "displayName": "Alien_Gono"
            },
            {
                "type": "steam",
                "displayName": "pienyoureye"
            },
            {
                "type": "psn",
                "displayName": "Alien_Gono"
            }
        ]
    },
    "8c6a369b22ba457283c5fa7113ce6f4a": {
        "displayName": "\u30b7\u1515\u144c\u15f0\u15f0 \u1515\u14aaI\u161c\u157cT",
        "externalPlatforms": [
            {
                "type": "psn",
                "displayName": "khillacase-_-"
            }
        ]
    },
    "8272c263db1d4cbea42451a03af9f209": {
        "displayName": "toxcwill",
        "externalPlatforms": [
            {
                "type": "psn",
                "displayName": "SyZe-NovA"
            }
        ]
    },
    "63a0887e3fb64ce088c8a258d5905935": {
        "displayName": "ttv_kazzy_67",
        "externalPlatforms": [
            {
                "type": "xbl",
                "displayName": "kazzb67"
            },
            {
                "type": "nintendo",
                "displayName": "ttv_kazzy_67"
            },
            {
                "type": "psn",
                "displayName": "Kazzy_xcx"
            }
        ]
    },
    "6d069376d23a40969f3dc3e881e8d415": {
        "displayName": "Vamios.",
        "externalPlatforms": [
            {
                "type": "xbl",
                "displayName": "Vamios"
            }
        ]
    },
    "3082e970ffd94381ae98861575bbefd4": {
        "displayName": "RocThomasRocks",
        "externalPlatforms": [
            {
                "type": "psn",
                "displayName": "RocThomasRocks"
            }
        ]
    },
    "016178ceb33745a2b8e00a40c8addded": {
        "displayName": "chasehayes123",
        "externalPlatforms": [
            {
                "type": "psn",
                "displayName": "chasehayes123"
            }
        ]
    },
    "e483aa88d405486a8979f6d3c057b759": {
        "displayName": "LuvKaizen",
        "externalPlatforms": [
            {
                "type": "xbl",
                "displayName": "LuvsKaizen"
            },
            {
                "type": "psn",
                "displayName": "NeoWillow_"
            }
        ]
    },
    "48f3aa43a17c4555ac6773a54228bdfa": {
        "displayName": "N\u00e1zg\u00fbl Sheik",
        "externalPlatforms": [
            {
                "type": "psn",
                "displayName": "Nazgul_Sheik"
            }
        ]
    },
    "068e9a21764449088cfb447905819410": {
        "displayName": "OGNXTDOOR-_-",
        "externalPlatforms": [
            {
                "type": "psn",
                "displayName": "OGNXTDOOR-_-"
            }
        ]
    },
    "b978f0704e124ac188ff9e5e4520cd66": {
        "displayName": "Danixo89",
        "externalPlatforms": [
            {
                "type": "xbl",
                "displayName": "foxydanielxx"
            },
            {
                "type": "nintendo",
                "displayName": "Danixo89"
            },
            {
                "type": "steam",
                "displayName": "Dnlx_Wolf"
            },
            {
                "type": "psn",
                "displayName": "foxydanielx"
            }
        ]
    },
    "15307c66ae7441688bd27b2642444e5b": {
        "displayName": "Hi7896",
        "externalPlatforms": [
            {
                "type": "xbl",
                "displayName": "HermTh3Worm"
            }
        ]
    },
    "8a8963b6cc1845d286c4bc133921961e": {
        "displayName": "BRENCHA",
        "externalPlatforms": [
            {
                "type": "psn",
                "displayName": "BRENCHA"
            }
        ]
    },
    "c098aa7f3cd944f68f876a6905bcbb3c": {
        "displayName": "Drainion",
        "externalPlatforms": [
            {
                "type": "xbl",
                "displayName": "DOGEYES 543"
            },
            {
                "type": "steam",
                "displayName": "Drainion"
            },
            {
                "type": "psn",
                "displayName": "Drainion"
            }
        ]
    },
    "1505e147e994465cba85ed1d99696ac4": {
        "displayName": "TheHomieRich",
        "externalPlatforms": [
            {
                "type": "xbl",
                "displayName": "Mega Milkerz"
            }
        ]
    },
    "8c889cefd5774051af7b2303bef5aeb4": {
        "displayName": "EternalSlaya",
        "externalPlatforms": [
            {
                "type": "xbl",
                "displayName": "EternalSlaya"
            }
        ]
    },
    "3ac13b8f6c4649b1bdaa19e3a374be90": {
        "displayName": "Brunogzt",
        "externalPlatforms": [
            {
                "type": "xbl",
                "displayName": "Brunogztale"
            }
        ]
    },
    "74991fea2ee347b7a94c3fb97fe90005": {
        "displayName": "FearlessGold214",
        "externalPlatforms": [
            {
                "type": "xbl",
                "displayName": "TIM TO PRO"
            },
            {
                "type": "psn",
                "displayName": "FearlessGold214"
            }
        ]
    },
    "3623dab9528e4443896f3e0c861a75e9": {
        "displayName": "t-girl jane",
        "externalPlatforms": [
            {
                "type": "xbl",
                "displayName": "sassyfigboi"
            },
            {
                "type": "nintendo",
                "displayName": "t-girl jane"
            },
            {
                "type": "steam",
                "displayName": "Figgy"
            },
            {
                "type": "psn",
                "displayName": "FiggyCat25"
            }
        ]
    },
    "1856d805c69a4260a567e8a7873b6fa4": {
        "displayName": "OGkeanu04",
        "externalPlatforms": [
            {
                "type": "psn",
                "displayName": "OGkeanu04"
            }
        ]
    },
    "e7f0a17514254b548c1f0fc65b4c1e64": {
        "displayName": "MeowWalkin",
        "externalPlatforms": [
            {
                "type": "nintendo",
                "displayName": "MeowWalkin"
            },
            {
                "type": "psn",
                "displayName": "AFMeowWalkin"
            }
        ]
    },
    "2cb5d40e7146407eb195de8c8e453ed1": {
        "displayName": "Astro-Waffle-",
        "externalPlatforms": [
            {
                "type": "xbl",
                "displayName": "GrainedWaffle"
            },
            {
                "type": "nintendo",
                "displayName": "Astro-Waffle-"
            },
            {
                "type": "psn",
                "displayName": "Astro_Waffle1516"
            }
        ]
    },
    "8affb32c7b894a1588887c2260b0556d": {
        "displayName": "pogoy21111",
        "externalPlatforms": [
            {
                "type": "psn",
                "displayName": "killer_twin_ant2"
            }
        ]
    }
}